mlbootstrap/__init__.py
mlbootstrap/base.py
mlbootstrap/bootstrap.py
mlbootstrap/fetch.py
mlbootstrap/model.py
mlbootstrap/nlp.py
mlbootstrap/preprocess.py
mlbootstrap-0.0.5.dist-info/METADATA
mlbootstrap-0.0.5.dist-info/RECORD
mlbootstrap-0.0.5.dist-info/WHEEL
mlbootstrap-0.0.5.dist-info/top_level.txt
